datasette_sentry.py
datasette_sentry-0.4.dist-info/LICENSE
datasette_sentry-0.4.dist-info/METADATA
datasette_sentry-0.4.dist-info/WHEEL
datasette_sentry-0.4.dist-info/entry_points.txt
datasette_sentry-0.4.dist-info/top_level.txt
datasette_sentry-0.4.dist-info/RECORD
