Metadata-Version: 2.1
Name: datasette-sentry
Version: 0.4
Summary: Datasette plugin for configuring Sentry
Home-page: https://github.com/simonw/datasette-sentry
Author: Simon Willison
License: Apache License, Version 2.0
Classifier: License :: OSI Approved :: Apache Software License
Classifier: Programming Language :: Python :: 3.7
Classifier: Programming Language :: Python :: 3.8
License-File: LICENSE
Requires-Dist: sentry-sdk
Requires-Dist: datasette >=0.62
Provides-Extra: test
Requires-Dist: pytest ; extra == 'test'
Requires-Dist: pytest-asyncio ; extra == 'test'
